novelai_python-0.7.12.dist-info/METADATA
novelai_python-0.7.12.dist-info/WHEEL
novelai_python-0.7.12.dist-info/entry_points.txt
novelai_python-0.7.12.dist-info/licenses/LICENSE
novelai_python-0.7.12.dist-info/licenses/NOTICE.MD
novelai_python/__init__.py
novelai_python/_enum.py
novelai_python/_exceptions.py
novelai_python/_response/__init__.py
novelai_python/_response/ai/__init__.py
novelai_python/_response/ai/generate.py
novelai_python/_response/ai/generate_image.py
novelai_python/_response/ai/generate_stream.py
novelai_python/_response/ai/generate_voice.py
novelai_python/_response/ai/upscale.py
novelai_python/_response/schema.py
novelai_python/_response/user/__init__.py
novelai_python/_response/user/information.py
novelai_python/_response/user/login.py
novelai_python/_response/user/subscription.py
novelai_python/credential/ApiToken.py
novelai_python/credential/JwtToken.py
novelai_python/credential/UserAuth.py
novelai_python/credential/__init__.py
novelai_python/credential/_base.py
novelai_python/sdk/__init__.py
novelai_python/sdk/ai/LICENSE
novelai_python/sdk/ai/__init__.py
novelai_python/sdk/ai/_const.py
novelai_python/sdk/ai/_cost.py
novelai_python/sdk/ai/_enum.py
novelai_python/sdk/ai/augment_image/__init__.py
novelai_python/sdk/ai/augment_image/_enum.py
novelai_python/sdk/ai/generate/__init__.py
novelai_python/sdk/ai/generate/_const.py
novelai_python/sdk/ai/generate/_enum.py
novelai_python/sdk/ai/generate/_schema.py
novelai_python/sdk/ai/generate/themes.json
novelai_python/sdk/ai/generate_image/__init__.py
novelai_python/sdk/ai/generate_image/params.py
novelai_python/sdk/ai/generate_image/schema.py
novelai_python/sdk/ai/generate_image/suggest_tags.py
novelai_python/sdk/ai/generate_image/tokenizer.py
novelai_python/sdk/ai/generate_stream.py
novelai_python/sdk/ai/generate_voice/__init__.py
novelai_python/sdk/ai/generate_voice/_enum.py
novelai_python/sdk/ai/upscale.py
novelai_python/sdk/schema.py
novelai_python/sdk/user/__init__.py
novelai_python/sdk/user/information.py
novelai_python/sdk/user/login.py
novelai_python/sdk/user/subscription.py
novelai_python/server.py
novelai_python/tokenizer/__init__.py
novelai_python/tokenizer/clip_simple_tokenizer.py
novelai_python-0.7.12.dist-info/RECORD
