Metadata-Version: 2.1
Name: novelai-python
Version: 0.7.12
Summary: NovelAI Python Binding With Pydantic
Author-Email: sudoskys <coldlando@hotmail.com>
License: Apache License 2.0
Project-URL: Repository, https://github.com/LlmKira/novelai-python/
Project-URL: Issues, https://github.com/LlmKira/novelai-python/issues
Requires-Python: >=3.9
Requires-Dist: elara>=0.5.5
Requires-Dist: loguru>=0.7.2
Requires-Dist: pydantic-settings>=2.1.0
Requires-Dist: pydantic>=2.9.0
Requires-Dist: httpx>=0.26.0
Requires-Dist: shortuuid>=1.0.11
Requires-Dist: Pillow>=10.2.0
Requires-Dist: curl-cffi>=0.11.3
Requires-Dist: fastapi>=0.109.0
Requires-Dist: uvicorn[standard]>=0.27.0.post1
Requires-Dist: numpy>=1.24.4
Requires-Dist: argon2-cffi>=23.1.0
Requires-Dist: opencv-python>=4.8.1.78
Requires-Dist: fake-useragent>=1.4.0
Requires-Dist: tenacity>=8.2.3
Requires-Dist: sentencepiece>=0.2.0
Requires-Dist: pynacl>=1.5.0
Requires-Dist: ftfy>=6.2.0
Requires-Dist: regex>=2023.12.25
Requires-Dist: tokenizers>=0.15.2
Requires-Dist: json-repair>=0.29.4
Requires-Dist: robust-downloader>=0.0.2
Requires-Dist: bchlib>=2.1.3
Requires-Dist: arrow>=1.3.0
Provides-Extra: testing
Requires-Dist: pytest>=7.4.4; extra == "testing"
Requires-Dist: pytest-asyncio>=0.23.4; extra == "testing"
